nbslide/__init__.py
nbslide/_version.py
nbslide/labextension/build_log.json
nbslide/labextension/package.json
nbslide/labextension/schemas/nbslide/main.json
nbslide/labextension/schemas/nbslide/package.json.orig
nbslide/labextension/static/lib_index_js.4e90c9679512f2f64773.js
nbslide/labextension/static/lib_index_js.4e90c9679512f2f64773.js.map
nbslide/labextension/static/lib_index_js.524684d3b32e8bb86cfe.js
nbslide/labextension/static/lib_index_js.524684d3b32e8bb86cfe.js.map
nbslide/labextension/static/lib_index_js.583f0739f8d5673eb35f.js
nbslide/labextension/static/lib_index_js.583f0739f8d5673eb35f.js.map
nbslide/labextension/static/lib_index_js.9190eac3a1d7bfe1d4e3.js
nbslide/labextension/static/lib_index_js.9190eac3a1d7bfe1d4e3.js.map
nbslide/labextension/static/lib_index_js.b149f7b7a2ba80144a84.js
nbslide/labextension/static/lib_index_js.b149f7b7a2ba80144a84.js.map
nbslide/labextension/static/lib_index_js.ca974bf7b5ecb3219e7d.js
nbslide/labextension/static/lib_index_js.ca974bf7b5ecb3219e7d.js.map
nbslide/labextension/static/lib_index_js.d333d3262a31d3dcf329.js
nbslide/labextension/static/lib_index_js.d333d3262a31d3dcf329.js.map
nbslide/labextension/static/lib_index_js.d9a89b8c74e2ae6e9f0d.js
nbslide/labextension/static/lib_index_js.d9a89b8c74e2ae6e9f0d.js.map
nbslide/labextension/static/lib_index_js.dbae365cb43ff0ab45b9.js
nbslide/labextension/static/lib_index_js.dbae365cb43ff0ab45b9.js.map
nbslide/labextension/static/lib_index_js.e473407bc559da3d9326.js
nbslide/labextension/static/lib_index_js.e473407bc559da3d9326.js.map
nbslide/labextension/static/remoteEntry.0ec3d6290ccb0e773b5a.js.map
nbslide/labextension/static/remoteEntry.0fe283cb1f661aa5cd4b.js.map
nbslide/labextension/static/remoteEntry.1a89ac64356d428e6563.js.map
nbslide/labextension/static/remoteEntry.2391700252b34c86e8c5.js.map
nbslide/labextension/static/remoteEntry.439d3819338a45097390.js.map
nbslide/labextension/static/remoteEntry.672671ca795a08293b4d.js.map
nbslide-0.1.1.dist-info/LICENSE
nbslide-0.1.1.dist-info/METADATA
nbslide-0.1.1.dist-info/WHEEL
nbslide-0.1.1.dist-info/top_level.txt
nbslide-0.1.1.dist-info/RECORD
