Metadata-Version: 2.1
Name: nbslide
Version: 0.1.1
Summary: Slideshow extension for JupyterLab
Home-page: https://github.com/JoaoFelipe/nbslide
Author: Joao Felipe Pimentel
Author-email: joaofelipenp@gmail.com
License: BSD-3-Clause
Keywords: Jupyter,JupyterLab,JupyterLab3
Platform: Linux
Platform: Mac OS X
Platform: Windows
Classifier: License :: OSI Approved :: BSD License
Classifier: Programming Language :: Python
Classifier: Programming Language :: Python :: 3
Classifier: Programming Language :: Python :: 3.6
Classifier: Programming Language :: Python :: 3.7
Classifier: Programming Language :: Python :: 3.8
Classifier: Programming Language :: Python :: 3.9
Classifier: Framework :: Jupyter
Requires-Python: >=3.6
